vmutils
