Metadata-Version: 1.0
Name: vmutils
Version: 0.5.1
Summary: Video Manager Utils
Home-page: https://github.com/emilianobilli/vmutils
Author: Nicolas Pajoni, Emiliano Billi
Author-email: nicolaspajoni@gmail.com, emiliano.billi@gmail.com
License: GPL
Platform: UNKNOWN
